<?xml version="1.0" encoding="UTF-8"?>
<qes:espresso xsi:schemaLocation="http://www.quantum-espresso.org/ns/qes/qes-1.0 http://www.quantum-espresso.org/ns/qes/qes_030920.xsd" Units="Hartree atomic units" xmlns:xsi="http://www.w3.org/2001/XMLSchema-instance" xmlns:qes="http://www.quantum-espresso.org/ns/qes/qes-1.0">
  <!--All quantities are in Hartree atomic units unless otherwise specified-->
  <general_info>
    <xml_format NAME="QEXSD" VERSION="20.04.20">QEXSD_20.04.20</xml_format>
    <creator NAME="PWSCF" VERSION="6.7MaX">XML file generated by PWSCF</creator>
    <created DATE="11Jun2026" TIME="21: 2: 0">This run was terminated on:  21: 2: 0  11 Jun 2026</created>
    <job></job>
  </general_info>
  <parallel_info>
    <nprocs>64</nprocs>
    <nthreads>1</nthreads>
    <ntasks>1</ntasks>
    <nbgrp>1</nbgrp>
    <npool>1</npool>
    <ndiag>64</ndiag>
  </parallel_info>
  <input>
    <control_variables>
      <title></title>
      <calculation>relax</calculation>
      <restart_mode>from_scratch</restart_mode>
      <prefix>MoS2</prefix>
      <pseudo_dir>/public3/home/a2s002871/MoS2/pseudo/</pseudo_dir>
      <outdir>./tmp/</outdir>
      <stress>false</stress>
      <forces>false</forces>
      <wf_collect>true</wf_collect>
      <disk_io>low</disk_io>
      <max_seconds>10000000</max_seconds>
      <nstep>50</nstep>
      <etot_conv_thr>5.000000000000000e-6</etot_conv_thr>
      <forc_conv_thr>5.000000000000000e-5</forc_conv_thr>
      <press_conv_thr>5.000000000000000e-1</press_conv_thr>
      <verbosity>low</verbosity>
      <print_every>100000</print_every>
    </control_variables>
    <atomic_species ntyp="2">
      <species name="Mo">
        <mass>9.595000000000001e1</mass>
        <pseudo_file>Mo.pbe-spn-rrkjus_psl.1.0.0.UPF</pseudo_file>
      </species>
      <species name="S">
        <mass>3.206000000000000e1</mass>
        <pseudo_file>S.pbe-n-rrkjus_psl.1.0.0.UPF</pseudo_file>
      </species>
    </atomic_species>
    <atomic_structure nat="3" alat="6.028226337556e0" bravais_index="4">
      <atomic_positions>
        <atom name="Mo" index="1">-3.014113083533162e-9 3.480398100464514e0 1.417294593469328e1</atom>
        <atom name="S" index="2">3.014113171792217e0 1.740199047621958e0 1.550520285255445e1</atom>
        <atom name="S" index="3">3.014113171792217e0 1.740199047621958e0 1.284068901683211e1</atom>
      </atomic_positions>
      <cell>
        <a1>6.028226337556207e0 0.000000000000000e0 0.000000000000000e0</a1>
        <a2>-3.014113168778104e0 5.220597148086472e0 0.000000000000000e0</a2>
        <a3>0.000000000000000e0 0.000000000000000e0 2.834589186938656e1</a3>
      </cell>
    </atomic_structure>
    <dft>
      <functional>PBE</functional>
    </dft>
    <spin>
      <lsda>false</lsda>
      <noncolin>false</noncolin>
      <spinorbit>false</spinorbit>
    </spin>
    <bands>
      <smearing degauss="1.000000000000e-1">mv</smearing>
      <tot_charge>0.000000000000000e0</tot_charge>
      <occupations>smearing</occupations>
    </bands>
    <basis>
      <gamma_only>true</gamma_only>
      <ecutwfc>3.000000000000000e1</ecutwfc>
      <ecutrho>1.200000000000000e2</ecutrho>
    </basis>
    <electron_control>
      <diagonalization>davidson</diagonalization>
      <mixing_mode>plain</mixing_mode>
      <mixing_beta>7.000000000000000e-1</mixing_beta>
      <conv_thr>4.999999999999999e-10</conv_thr>
      <mixing_ndim>8</mixing_ndim>
      <max_nstep>100</max_nstep>
      <real_space_q>false</real_space_q>
      <real_space_beta>false</real_space_beta>
      <tq_smoothing>false</tq_smoothing>
      <tbeta_smoothing>false</tbeta_smoothing>
      <diago_thr_init>0.000000000000000e0</diago_thr_init>
      <diago_full_acc>false</diago_full_acc>
      <diago_cg_maxiter>20</diago_cg_maxiter>
      <diago_ppcg_maxiter>20</diago_ppcg_maxiter>
    </electron_control>
    <k_points_IBZ>
      <nk>1</nk>
      <k_point weight="1.000000000000e0">0.000000000000000e0 0.000000000000000e0 0.000000000000000e0</k_point>
    </k_points_IBZ>
    <ion_control>
      <ion_dynamics>bfgs</ion_dynamics>
      <upscale>1.000000000000000e2</upscale>
      <remove_rigid_rot>false</remove_rigid_rot>
      <refold_pos>false</refold_pos>
      <bfgs>
        <ndim>1</ndim>
        <trust_radius_min>1.000000000000000e-4</trust_radius_min>
        <trust_radius_max>8.000000000000000e-1</trust_radius_max>
        <trust_radius_init>5.000000000000000e-1</trust_radius_init>
        <w1>1.000000000000000e-2</w1>
        <w2>5.000000000000000e-1</w2>
      </bfgs>
    </ion_control>
    <cell_control>
      <cell_dynamics>none</cell_dynamics>
      <pressure>0.000000000000000e0</pressure>
      <wmass>1.600700000000000e2</wmass>
      <cell_factor>0.000000000000000e0</cell_factor>
      <fix_volume>false</fix_volume>
      <fix_area>false</fix_area>
      <isotropic>false</isotropic>
    </cell_control>
    <symmetry_flags>
      <nosym>false</nosym>
      <nosym_evc>false</nosym_evc>
      <noinv>false</noinv>
      <no_t_rev>false</no_t_rev>
      <force_symmorphic>false</force_symmorphic>
      <use_all_frac>false</use_all_frac>
    </symmetry_flags>
    <free_positions rank="2" dims="3 3" order="F">
      1 1 1
      1 1 1
      1 1 1
      </free_positions>
  </input>
  <step n_step="1">
    <scf_conv>
      <convergence_achieved>true</convergence_achieved>
      <n_scf_steps>20</n_scf_steps>
      <scf_error>8.501515741539309e-11</scf_error>
    </scf_conv>
    <atomic_structure nat="3" alat="6.028226337556e0">
      <atomic_positions>
        <atom name="Mo" index="1">-3.014113083533162e-9 3.480398100464514e0 1.417294593469328e1</atom>
        <atom name="S" index="2">3.014113171792217e0 1.740199047621958e0 1.550520285255445e1</atom>
        <atom name="S" index="3">3.014113171792217e0 1.740199047621958e0 1.284068901683211e1</atom>
      </atomic_positions>
      <cell>
        <a1>6.028226337556207e0 0.000000000000000e0 0.000000000000000e0</a1>
        <a2>-3.014113168778104e0 5.220597148086472e0 0.000000000000000e0</a2>
        <a3>0.000000000000000e0 0.000000000000000e0 2.834589186938656e1</a3>
      </cell>
    </atomic_structure>
    <total_energy>
      <etot>-8.978319061278857e1</etot>
      <eband>-1.822351517326246e1</eband>
      <ehart>2.273586060957057e2</ehart>
      <vtxc>-1.789371877872211e1</vtxc>
      <etxc>-1.580101335564555e1</etxc>
      <ewald>1.538285123538402e2</ewald>
      <demet>-1.223044727045080e-1</demet>
    </total_energy>
    <forces rank="2" dims="3 3" order="F">
      0.000000000000000e0 -4.075289167580981e-23 0.000000000000000e0
      8.823259867232293e-24 5.094111459476226e-24 1.335657614657021e0
      8.823259867232293e-24 1.782939010816679e-23 -1.335657614657021e0
      </forces>
  </step>
  <step n_step="2">
    <scf_conv>
      <convergence_achieved>true</convergence_achieved>
      <n_scf_steps>15</n_scf_steps>
      <scf_error>8.576742035107408e-10</scf_error>
    </scf_conv>
    <atomic_structure nat="3" alat="6.028226337556e0">
      <atomic_positions>
        <atom name="Mo" index="1">-3.014113083533162e-9 3.480398100464513e0 1.417294593469328e1</atom>
        <atom name="S" index="2">3.014113171792217e0 1.740199047621958e0 1.600520285255445e1</atom>
        <atom name="S" index="3">3.014113171792217e0 1.740199047621958e0 1.234068901683211e1</atom>
      </atomic_positions>
      <cell>
        <a1>6.028226337556207e0 0.000000000000000e0 0.000000000000000e0</a1>
        <a2>-3.014113168778104e0 5.220597148086472e0 0.000000000000000e0</a2>
        <a3>0.000000000000000e0 0.000000000000000e0 2.834589186938656e1</a3>
      </cell>
    </atomic_structure>
    <total_energy>
      <etot>-9.037738761859137e1</etot>
      <eband>-1.655058635786281e1</eband>
      <ehart>2.131410658988693e2</ehart>
      <vtxc>-1.741351347388122e1</vtxc>
      <etxc>-1.542506952969099e1</etxc>
      <ewald>1.374652049516774e2</ewald>
      <demet>-1.393322523344977e-1</demet>
    </total_energy>
    <forces rank="2" dims="3 3" order="F">
      0.000000000000000e0 0.000000000000000e0 0.000000000000000e0
      3.614007241618347e-20 1.877893248421316e-19 2.698204737684676e-1
      -7.228014483236694e-20 4.173096107602923e-20 -2.698204737684676e-1
      </forces>
  </step>
  <step n_step="3">
    <scf_conv>
      <convergence_achieved>true</convergence_achieved>
      <n_scf_steps>11</n_scf_steps>
      <scf_error>3.705267547732607e-10</scf_error>
    </scf_conv>
    <atomic_structure nat="3" alat="6.028226337556e0">
      <atomic_positions>
        <atom name="Mo" index="1">-3.014113083533162e-9 3.480398100464511e0 1.417294593469327e1</atom>
        <atom name="S" index="2">3.014113171792217e0 1.740199047621957e0 1.613177963591908e1</atom>
        <atom name="S" index="3">3.014113171792217e0 1.740199047621957e0 1.221411223346747e1</atom>
      </atomic_positions>
      <cell>
        <a1>6.028226337556207e0 0.000000000000000e0 0.000000000000000e0</a1>
        <a2>-3.014113168778104e0 5.220597148086472e0 0.000000000000000e0</a2>
        <a3>0.000000000000000e0 0.000000000000000e0 2.834589186938656e1</a3>
      </cell>
    </atomic_structure>
    <total_energy>
      <etot>-9.043766366078932e1</etot>
      <eband>-1.624508962910227e1</eband>
      <ehart>2.093620787481928e2</ehart>
      <vtxc>-1.733562972415967e1</vtxc>
      <etxc>-1.536679047540112e1</etxc>
      <ewald>1.333119590049816e2</ewald>
      <demet>-1.114694662623096e-1</demet>
    </total_energy>
    <forces rank="2" dims="3 3" order="F">
      2.168404344971009e-19 2.921167275322047e-19 0.000000000000000e0
      1.445602896647339e-19 -1.669238443041170e-19 2.075696617413223e-1
      -1.445602896647339e-19 6.207133318276446e-37 -2.075696617413223e-1
      </forces>
  </step>
  <step n_step="4">
    <scf_conv>
      <convergence_achieved>true</convergence_achieved>
      <n_scf_steps>12</n_scf_steps>
      <scf_error>8.842186704017879e-10</scf_error>
    </scf_conv>
    <atomic_structure nat="3" alat="6.028226337556e0">
      <atomic_positions>
        <atom name="Mo" index="1">-3.014113083533162e-9 3.480398100464507e0 1.417294593469326e1</atom>
        <atom name="S" index="2">3.014113171792217e0 1.740199047621956e0 1.627101409762019e1</atom>
        <atom name="S" index="3">3.014113171792217e0 1.740199047621956e0 1.207487777176635e1</atom>
      </atomic_positions>
      <cell>
        <a1>6.028226337556207e0 0.000000000000000e0 0.000000000000000e0</a1>
        <a2>-3.014113168778104e0 5.220597148086472e0 0.000000000000000e0</a2>
        <a3>0.000000000000000e0 0.000000000000000e0 2.834589186938656e1</a3>
      </cell>
    </atomic_structure>
    <total_energy>
      <etot>-9.048614296586084e1</etot>
      <eband>-1.590416814748360e1</eband>
      <ehart>2.051853007252792e2</ehart>
      <vtxc>-1.725219942048599e1</vtxc>
      <etxc>-1.530464160426024e1</etxc>
      <ewald>1.287293129018294e2</ewald>
      <demet>-7.361752503044171e-2</demet>
    </total_energy>
    <forces rank="2" dims="3 3" order="F">
      0.000000000000000e0 3.338476886082339e-19 0.000000000000000e0
      3.614007241618347e-20 2.086548053801462e-20 1.401534944498729e-1
      3.614007241618347e-20 2.086548053801462e-20 -1.401534944498729e-1
      </forces>
  </step>
  <step n_step="5">
    <scf_conv>
      <convergence_achieved>true</convergence_achieved>
      <n_scf_steps>12</n_scf_steps>
      <scf_error>4.326349225225877e-12</scf_error>
    </scf_conv>
    <atomic_structure nat="3" alat="6.028226337556e0">
      <atomic_positions>
        <atom name="Mo" index="1">-3.014117768406136e-9 3.480398100464504e0 1.417294593469324e1</atom>
        <atom name="S" index="2">3.014113171792217e0 1.740199047621952e0 1.647986579017186e1</atom>
        <atom name="S" index="3">3.014113171792217e0 1.740199047621952e0 1.186602607921470e1</atom>
      </atomic_positions>
      <cell>
        <a1>6.028226337556207e0 0.000000000000000e0 0.000000000000000e0</a1>
        <a2>-3.014113168778104e0 5.220597148086472e0 0.000000000000000e0</a2>
        <a3>0.000000000000000e0 0.000000000000000e0 2.834589186938656e1</a3>
      </cell>
    </atomic_structure>
    <total_energy>
      <etot>-9.052549416894548e1</etot>
      <eband>-1.536640404580600e1</eband>
      <ehart>1.988967533170845e2</ehart>
      <vtxc>-1.712793003540970e1</vtxc>
      <etxc>-1.521209517020123e1</etxc>
      <ewald>1.218368552628275e2</ewald>
      <demet>-1.500610551909638e-2</demet>
    </total_energy>
    <forces rank="2" dims="3 3" order="F">
      2.205814966808073e-24 -9.471333798639597e-42 0.000000000000000e0
      1.102907483404037e-24 -1.910291797303585e-24 4.087073944109298e-2
      0.000000000000000e0 0.000000000000000e0 -4.087073944109298e-2
      </forces>
  </step>
  <step n_step="6">
    <scf_conv>
      <convergence_achieved>true</convergence_achieved>
      <n_scf_steps>9</n_scf_steps>
      <scf_error>9.501603341072162e-10</scf_error>
    </scf_conv>
    <atomic_structure nat="3" alat="6.028226337556e0">
      <atomic_positions>
        <atom name="Mo" index="1">-3.014118437673703e-9 3.480398100464502e0 1.417294593469322e1</atom>
        <atom name="S" index="2">3.014113171792217e0 1.740199047621949e0 1.656584167900932e1</atom>
        <atom name="S" index="3">3.014113171792217e0 1.740199047621949e0 1.178005019037725e1</atom>
      </atomic_positions>
      <cell>
        <a1>6.028226337556207e0 0.000000000000000e0 0.000000000000000e0</a1>
        <a2>-3.014113168778104e0 5.220597148086472e0 0.000000000000000e0</a2>
        <a3>0.000000000000000e0 0.000000000000000e0 2.834589186938656e1</a3>
      </cell>
    </atomic_structure>
    <total_energy>
      <etot>-9.052914499403327e1</etot>
      <eband>-1.516630459987190e1</eband>
      <ehart>1.962742676095779e2</ehart>
      <vtxc>-1.707374201345241e1</vtxc>
      <etxc>-1.517151462419347e1</etxc>
      <ewald>1.189974484886301e2</ewald>
      <demet>1.196009110242820e-2</demet>
    </total_energy>
    <forces rank="2" dims="3 3" order="F">
      0.000000000000000e0 -1.591909831086320e-25 0.000000000000000e0
      0.000000000000000e0 0.000000000000000e0 2.403077546906087e-3
      1.723292942818807e-26 -9.949436444289503e-27 -2.403077546906087e-3
      </forces>
  </step>
  <step n_step="7">
    <scf_conv>
      <convergence_achieved>true</convergence_achieved>
      <n_scf_steps>8</n_scf_steps>
      <scf_error>4.854999680406910e-11</scf_error>
    </scf_conv>
    <atomic_structure nat="3" alat="6.028226337556e0">
      <atomic_positions>
        <atom name="Mo" index="1">-3.014118437673703e-9 3.480398100464501e0 1.417294593469322e1</atom>
        <atom name="S" index="2">3.014113171792217e0 1.740199047621948e0 1.657121259883826e1</atom>
        <atom name="S" index="3">3.014113171792217e0 1.740199047621948e0 1.177467927054831e1</atom>
      </atomic_positions>
      <cell>
        <a1>6.028226337556207e0 0.000000000000000e0 0.000000000000000e0</a1>
        <a2>-3.014113168778104e0 5.220597148086472e0 0.000000000000000e0</a2>
        <a3>0.000000000000000e0 0.000000000000000e0 2.834589186938656e1</a3>
      </cell>
    </atomic_structure>
    <total_energy>
      <etot>-9.052915858112881e1</etot>
      <eband>-1.515432058761990e1</eband>
      <ehart>1.961099313716079e2</ehart>
      <vtxc>-1.707041671884301e1</vtxc>
      <etxc>-1.516902787331096e1</etxc>
      <ewald>1.188200981863601e2</ewald>
      <demet>1.357683940060989e-2</demet>
    </total_energy>
    <forces rank="2" dims="3 3" order="F">
      0.000000000000000e0 -7.959549155431603e-26 0.000000000000000e0
      0.000000000000000e0 -1.989887288857901e-26 1.496720946143077e-4
      -3.446585885637615e-26 3.979774577715801e-26 -1.496720946143077e-4
      </forces>
  </step>
  <step n_step="8">
    <scf_conv>
      <convergence_achieved>true</convergence_achieved>
      <n_scf_steps>7</n_scf_steps>
      <scf_error>1.689350233568681e-12</scf_error>
    </scf_conv>
    <atomic_structure nat="3" alat="6.028226337556e0">
      <atomic_positions>
        <atom name="Mo" index="1">-3.014118437673703e-9 3.480398100464501e0 1.417294593469322e1</atom>
        <atom name="S" index="2">3.014113171792217e0 1.740199047621948e0 1.657156933748908e1</atom>
        <atom name="S" index="3">3.014113171792217e0 1.740199047621948e0 1.177432253189748e1</atom>
      </atomic_positions>
      <cell>
        <a1>6.028226337556207e0 0.000000000000000e0 0.000000000000000e0</a1>
        <a2>-3.014113168778104e0 5.220597148086472e0 0.000000000000000e0</a2>
        <a3>0.000000000000000e0 0.000000000000000e0 2.834589186938656e1</a3>
      </cell>
    </atomic_structure>
    <total_energy>
      <etot>-9.052915863534887e1</etot>
      <eband>-1.515351115888490e1</eband>
      <ehart>1.960989926314088e2</ehart>
      <vtxc>-1.707019472181531e1</vtxc>
      <etxc>-1.516886179916383e1</etxc>
      <ewald>1.188083187132897e2</ewald>
      <demet>1.368356213512401e-2</demet>
    </total_energy>
    <forces rank="2" dims="3 3" order="F">
      0.000000000000000e0 0.000000000000000e0 0.000000000000000e0
      0.000000000000000e0 0.000000000000000e0 1.636716241288673e-6
      0.000000000000000e0 3.979774577715801e-26 -1.636716241288673e-6
      </forces>
  </step>
  <output>
    <convergence_info>
      <scf_conv>
        <convergence_achieved>true</convergence_achieved>
        <n_scf_steps>7</n_scf_steps>
        <scf_error>8.446751167843406e-13</scf_error>
      </scf_conv>
      <opt_conv>
        <convergence_achieved>true</convergence_achieved>
        <n_opt_steps>7</n_opt_steps>
        <grad_norm>4.629332612373513e-6</grad_norm>
      </opt_conv>
    </convergence_info>
    <algorithmic_info>
      <real_space_q>false</real_space_q>
      <real_space_beta>false</real_space_beta>
      <uspp>true</uspp>
      <paw>false</paw>
    </algorithmic_info>
    <atomic_species ntyp="2" pseudo_dir="/public3/home/a2s002871/MoS2/pseudo/">
      <species name="Mo">
        <mass>9.595000000000001e1</mass>
        <pseudo_file>Mo.pbe-spn-rrkjus_psl.1.0.0.UPF</pseudo_file>
      </species>
      <species name="S">
        <mass>3.206000000000000e1</mass>
        <pseudo_file>S.pbe-n-rrkjus_psl.1.0.0.UPF</pseudo_file>
      </species>
    </atomic_species>
    <atomic_structure nat="3" alat="6.028226337556e0" bravais_index="4">
      <atomic_positions>
        <atom name="Mo" index="1">-3.014118437673703e-9 3.480398100464500e0 1.417294593469322e1</atom>
        <atom name="S" index="2">3.014113171792217e0 1.740199047621948e0 1.657156933748908e1</atom>
        <atom name="S" index="3">3.014113171792217e0 1.740199047621948e0 1.177432253189748e1</atom>
      </atomic_positions>
      <cell>
        <a1>6.028226337556207e0 0.000000000000000e0 0.000000000000000e0</a1>
        <a2>-3.014113168778104e0 5.220597148086472e0 0.000000000000000e0</a2>
        <a3>0.000000000000000e0 0.000000000000000e0 2.834589186938656e1</a3>
      </cell>
    </atomic_structure>
    <symmetries>
      <nsym>12</nsym>
      <nrot>24</nrot>
      <space_group>0</space_group>
      <symmetry>
        <info name="identity">crystal_symmetry</info>
        <rotation rank="2" dims="3 3" order="F">
          1.000000000000000e0 0.000000000000000e0 0.000000000000000e0
          0.000000000000000e0 1.000000000000000e0 0.000000000000000e0
          0.000000000000000e0 0.000000000000000e0 1.000000000000000e0
          </rotation>
        <fractional_translation>0.000000000000000e0 0.000000000000000e0 0.000000000000000e0</fractional_translation>
        <equivalent_atoms nat="3" size="3">
          1 2 3
          </equivalent_atoms>
      </symmetry>
      <symmetry>
        <info name="180 deg rotation - cart. axis [0,1,0]">crystal_symmetry</info>
        <rotation rank="2" dims="3 3" order="F">
          -1.000000000000000e0 1.000000000000000e0 0.000000000000000e0
          0.000000000000000e0 1.000000000000000e0 0.000000000000000e0
          0.000000000000000e0 0.000000000000000e0 -1.000000000000000e0
          </rotation>
        <fractional_translation>0.000000000000000e0 0.000000000000000e0 0.000000000000000e0</fractional_translation>
        <equivalent_atoms nat="3" size="3">
          1 3 2
          </equivalent_atoms>
      </symmetry>
      <symmetry>
        <info name="120 deg rotation - cryst. axis [0,0,1]">crystal_symmetry</info>
        <rotation rank="2" dims="3 3" order="F">
          0.000000000000000e0 -1.000000000000000e0 0.000000000000000e0
          1.000000000000000e0 -1.000000000000000e0 0.000000000000000e0
          0.000000000000000e0 0.000000000000000e0 1.000000000000000e0
          </rotation>
        <fractional_translation>0.000000000000000e0 0.000000000000000e0 0.000000000000000e0</fractional_translation>
        <equivalent_atoms nat="3" size="3">
          1 2 3
          </equivalent_atoms>
      </symmetry>
      <symmetry>
        <info name="120 deg rotation - cryst. axis [0,0,-1]">crystal_symmetry</info>
        <rotation rank="2" dims="3 3" order="F">
          -1.000000000000000e0 1.000000000000000e0 0.000000000000000e0
          -1.000000000000000e0 0.000000000000000e0 0.000000000000000e0
          0.000000000000000e0 0.000000000000000e0 1.000000000000000e0
          </rotation>
        <fractional_translation>0.000000000000000e0 0.000000000000000e0 0.000000000000000e0</fractional_translation>
        <equivalent_atoms nat="3" size="3">
          1 2 3
          </equivalent_atoms>
      </symmetry>
      <symmetry>
        <info name="180 deg rotation - cryst. axis [1,-1,0]">crystal_symmetry</info>
        <rotation rank="2" dims="3 3" order="F">
          0.000000000000000e0 -1.000000000000000e0 0.000000000000000e0
          -1.000000000000000e0 0.000000000000000e0 0.000000000000000e0
          0.000000000000000e0 0.000000000000000e0 -1.000000000000000e0
          </rotation>
        <fractional_translation>0.000000000000000e0 0.000000000000000e0 0.000000000000000e0</fractional_translation>
        <equivalent_atoms nat="3" size="3">
          1 3 2
          </equivalent_atoms>
      </symmetry>
      <symmetry>
        <info name="180 deg rotation - cryst. axis [2,1,0]">crystal_symmetry</info>
        <rotation rank="2" dims="3 3" order="F">
          1.000000000000000e0 0.000000000000000e0 0.000000000000000e0
          1.000000000000000e0 -1.000000000000000e0 0.000000000000000e0
          0.000000000000000e0 0.000000000000000e0 -1.000000000000000e0
          </rotation>
        <fractional_translation>0.000000000000000e0 0.000000000000000e0 0.000000000000000e0</fractional_translation>
        <equivalent_atoms nat="3" size="3">
          1 3 2
          </equivalent_atoms>
      </symmetry>
      <symmetry>
        <info name="inv. 180 deg rotation - cart. axis [0,0,1]">crystal_symmetry</info>
        <rotation rank="2" dims="3 3" order="F">
          1.000000000000000e0 0.000000000000000e0 0.000000000000000e0
          0.000000000000000e0 1.000000000000000e0 0.000000000000000e0
          0.000000000000000e0 0.000000000000000e0 -1.000000000000000e0
          </rotation>
        <fractional_translation>0.000000000000000e0 0.000000000000000e0 0.000000000000000e0</fractional_translation>
        <equivalent_atoms nat="3" size="3">
          1 3 2
          </equivalent_atoms>
      </symmetry>
      <symmetry>
        <info name="inv. 180 deg rotation - cart. axis [1,0,0]">crystal_symmetry</info>
        <rotation rank="2" dims="3 3" order="F">
          -1.000000000000000e0 1.000000000000000e0 0.000000000000000e0
          0.000000000000000e0 1.000000000000000e0 0.000000000000000e0
          0.000000000000000e0 0.000000000000000e0 1.000000000000000e0
          </rotation>
        <fractional_translation>0.000000000000000e0 0.000000000000000e0 0.000000000000000e0</fractional_translation>
        <equivalent_atoms nat="3" size="3">
          1 2 3
          </equivalent_atoms>
      </symmetry>
      <symmetry>
        <info name="inv.  60 deg rotation - cryst. axis [0,0,1]">crystal_symmetry</info>
        <rotation rank="2" dims="3 3" order="F">
          -1.000000000000000e0 1.000000000000000e0 0.000000000000000e0
          -1.000000000000000e0 0.000000000000000e0 0.000000000000000e0
          0.000000000000000e0 0.000000000000000e0 -1.000000000000000e0
          </rotation>
        <fractional_translation>0.000000000000000e0 0.000000000000000e0 0.000000000000000e0</fractional_translation>
        <equivalent_atoms nat="3" size="3">
          1 3 2
          </equivalent_atoms>
      </symmetry>
      <symmetry>
        <info name="inv.  60 deg rotation - cryst. axis [0,0,-1]">crystal_symmetry</info>
        <rotation rank="2" dims="3 3" order="F">
          0.000000000000000e0 -1.000000000000000e0 0.000000000000000e0
          1.000000000000000e0 -1.000000000000000e0 0.000000000000000e0
          0.000000000000000e0 0.000000000000000e0 -1.000000000000000e0
          </rotation>
        <fractional_translation>0.000000000000000e0 0.000000000000000e0 0.000000000000000e0</fractional_translation>
        <equivalent_atoms nat="3" size="3">
          1 3 2
          </equivalent_atoms>
      </symmetry>
      <symmetry>
        <info name="inv. 180 deg rotation - cryst. axis [0,1,0]">crystal_symmetry</info>
        <rotation rank="2" dims="3 3" order="F">
          1.000000000000000e0 0.000000000000000e0 0.000000000000000e0
          1.000000000000000e0 -1.000000000000000e0 0.000000000000000e0
          0.000000000000000e0 0.000000000000000e0 1.000000000000000e0
          </rotation>
        <fractional_translation>0.000000000000000e0 0.000000000000000e0 0.000000000000000e0</fractional_translation>
        <equivalent_atoms nat="3" size="3">
          1 2 3
          </equivalent_atoms>
      </symmetry>
      <symmetry>
        <info name="inv. 180 deg rotation - cryst. axis [1,1,0]">crystal_symmetry</info>
        <rotation rank="2" dims="3 3" order="F">
          0.000000000000000e0 -1.000000000000000e0 0.000000000000000e0
          -1.000000000000000e0 0.000000000000000e0 0.000000000000000e0
          0.000000000000000e0 0.000000000000000e0 1.000000000000000e0
          </rotation>
        <fractional_translation>0.000000000000000e0 0.000000000000000e0 0.000000000000000e0</fractional_translation>
        <equivalent_atoms nat="3" size="3">
          1 2 3
          </equivalent_atoms>
      </symmetry>
      <symmetry>
        <info name="inversion">lattice_symmetry</info>
        <rotation rank="2" dims="3 3" order="F">
          -1.000000000000000e0 0.000000000000000e0 0.000000000000000e0
          0.000000000000000e0 -1.000000000000000e0 0.000000000000000e0
          0.000000000000000e0 0.000000000000000e0 -1.000000000000000e0
          </rotation>
      </symmetry>
      <symmetry>
        <info name="180 deg rotation - cart. axis [0,0,1]">lattice_symmetry</info>
        <rotation rank="2" dims="3 3" order="F">
          -1.000000000000000e0 0.000000000000000e0 0.000000000000000e0
          0.000000000000000e0 -1.000000000000000e0 0.000000000000000e0
          0.000000000000000e0 0.000000000000000e0 1.000000000000000e0
          </rotation>
      </symmetry>
      <symmetry>
        <info name="inv. 180 deg rotation - cart. axis [0,1,0]">lattice_symmetry</info>
        <rotation rank="2" dims="3 3" order="F">
          1.000000000000000e0 -1.000000000000000e0 0.000000000000000e0
          0.000000000000000e0 -1.000000000000000e0 0.000000000000000e0
          0.000000000000000e0 0.000000000000000e0 1.000000000000000e0
          </rotation>
      </symmetry>
      <symmetry>
        <info name="180 deg rotation - cart. axis [1,0,0]">lattice_symmetry</info>
        <rotation rank="2" dims="3 3" order="F">
          1.000000000000000e0 -1.000000000000000e0 0.000000000000000e0
          0.000000000000000e0 -1.000000000000000e0 0.000000000000000e0
          0.000000000000000e0 0.000000000000000e0 -1.000000000000000e0
          </rotation>
      </symmetry>
      <symmetry>
        <info name=" 60 deg rotation - cryst. axis [0,0,1]">lattice_symmetry</info>
        <rotation rank="2" dims="3 3" order="F">
          1.000000000000000e0 -1.000000000000000e0 0.000000000000000e0
          1.000000000000000e0 0.000000000000000e0 0.000000000000000e0
          0.000000000000000e0 0.000000000000000e0 1.000000000000000e0
          </rotation>
      </symmetry>
      <symmetry>
        <info name=" 60 deg rotation - cryst. axis [0,0,-1]">lattice_symmetry</info>
        <rotation rank="2" dims="3 3" order="F">
          0.000000000000000e0 1.000000000000000e0 0.000000000000000e0
          -1.000000000000000e0 1.000000000000000e0 0.000000000000000e0
          0.000000000000000e0 0.000000000000000e0 1.000000000000000e0
          </rotation>
      </symmetry>
      <symmetry>
        <info name="inv. 120 deg rotation - cryst. axis [0,0,1]">lattice_symmetry</info>
        <rotation rank="2" dims="3 3" order="F">
          0.000000000000000e0 1.000000000000000e0 0.000000000000000e0
          -1.000000000000000e0 1.000000000000000e0 0.000000000000000e0
          0.000000000000000e0 0.000000000000000e0 -1.000000000000000e0
          </rotation>
      </symmetry>
      <symmetry>
        <info name="inv. 120 deg rotation - cryst. axis [0,0,-1]">lattice_symmetry</info>
        <rotation rank="2" dims="3 3" order="F">
          1.000000000000000e0 -1.000000000000000e0 0.000000000000000e0
          1.000000000000000e0 0.000000000000000e0 0.000000000000000e0
          0.000000000000000e0 0.000000000000000e0 -1.000000000000000e0
          </rotation>
      </symmetry>
      <symmetry>
        <info name="inv. 180 deg rotation - cryst. axis [1,-1,0]">lattice_symmetry</info>
        <rotation rank="2" dims="3 3" order="F">
          0.000000000000000e0 1.000000000000000e0 0.000000000000000e0
          1.000000000000000e0 0.000000000000000e0 0.000000000000000e0
          0.000000000000000e0 0.000000000000000e0 1.000000000000000e0
          </rotation>
      </symmetry>
      <symmetry>
        <info name="inv. 180 deg rotation - cryst. axis [2,1,0]">lattice_symmetry</info>
        <rotation rank="2" dims="3 3" order="F">
          -1.000000000000000e0 0.000000000000000e0 0.000000000000000e0
          -1.000000000000000e0 1.000000000000000e0 0.000000000000000e0
          0.000000000000000e0 0.000000000000000e0 1.000000000000000e0
          </rotation>
      </symmetry>
      <symmetry>
        <info name="180 deg rotation - cryst. axis [0,1,0]">lattice_symmetry</info>
        <rotation rank="2" dims="3 3" order="F">
          -1.000000000000000e0 0.000000000000000e0 0.000000000000000e0
          -1.000000000000000e0 1.000000000000000e0 0.000000000000000e0
          0.000000000000000e0 0.000000000000000e0 -1.000000000000000e0
          </rotation>
      </symmetry>
      <symmetry>
        <info name="180 deg rotation - cryst. axis [1,1,0]">lattice_symmetry</info>
        <rotation rank="2" dims="3 3" order="F">
          0.000000000000000e0 1.000000000000000e0 0.000000000000000e0
          1.000000000000000e0 0.000000000000000e0 0.000000000000000e0
          0.000000000000000e0 0.000000000000000e0 -1.000000000000000e0
          </rotation>
      </symmetry>
    </symmetries>
    <basis_set>
      <gamma_only>true</gamma_only>
      <ecutwfc>3.000000000000000e1</ecutwfc>
      <ecutrho>1.200000000000000e2</ecutrho>
      <fft_grid nr1="30" nr2="30" nr3="144"></fft_grid>
      <fft_smooth nr1="30" nr2="30" nr3="144"></fft_smooth>
      <fft_box nr1="30" nr2="30" nr3="144"></fft_box>
      <ngm>27979</ngm>
      <ngms>27979</ngms>
      <npwx>3506</npwx>
      <reciprocal_lattice>
        <b1>1.000000000000000e0 5.773502691895848e-1 0.000000000000000e0</b1>
        <b2>0.000000000000000e0 1.154700538379170e0 0.000000000000000e0</b2>
        <b3>0.000000000000000e0 0.000000000000000e0 2.126666666666666e-1</b3>
      </reciprocal_lattice>
    </basis_set>
    <dft>
      <functional>PBE</functional>
    </dft>
    <magnetization>
      <lsda>false</lsda>
      <noncolin>false</noncolin>
      <spinorbit>false</spinorbit>
      <total>0.000000000000000e0</total>
      <absolute>0.000000000000000e0</absolute>
    </magnetization>
    <total_energy>
      <etot>-9.052915863534887e1</etot>
      <eband>-1.515351115888490e1</eband>
      <ehart>1.960989926314088e2</ehart>
      <vtxc>-1.707019472181531e1</vtxc>
      <etxc>-1.516886179916383e1</etxc>
      <ewald>1.188083187132897e2</ewald>
      <demet>1.368356213512401e-2</demet>
    </total_energy>
    <band_structure>
      <lsda>false</lsda>
      <noncolin>false</noncolin>
      <spinorbit>false</spinorbit>
      <nbnd>17</nbnd>
      <nelec>2.600000000000000e1</nelec>
      <num_of_atomic_wfc>18</num_of_atomic_wfc>
      <wf_collected>true</wf_collected>
      <fermi_energy>6.054301068862079e-2</fermi_energy>
      <starting_k_points>
        <nk>1</nk>
        <k_point weight="1.000000000000e0">0.000000000000000e0 0.000000000000000e0 0.000000000000000e0</k_point>
      </starting_k_points>
      <nks>1</nks>
      <occupations_kind>smearing</occupations_kind>
      <smearing degauss="1.000000000000e-1">mv</smearing>
      <ks_energies>
        <k_point weight="2.000000000000e0">0.000000000000000e0 0.000000000000000e0 0.000000000000000e0</k_point>
        <npw>3506</npw>
        <eigenvalues size="17">
          -2.175027080006616e0 -1.234034032642778e0 -1.227054736158856e0 -1.227054735889030e0 -5.574559492005074e-1
          -4.699700222652522e-1 -2.370547026338508e-1 -1.478259508692563e-1 -1.478259504062989e-1 -8.642217670126866e-2
          -8.642217508509027e-2 -2.442429371538750e-2 5.696002936568599e-2 1.090441731192630e-1 1.090441749004133e-1
          1.502889488280462e-1 1.502889496787327e-1
          </eigenvalues>
        <occupations size="17">
          1.000000000000000e0 1.000000000000000e0 1.000000000000000e0 1.000000000000000e0 1.000000000000034e0
          1.000000000223028e0 1.001652028005068e0 1.034189089685218e0 1.034189090056956e0 1.082610619423085e0
          1.082610619822761e0 9.708083317816417e-1 4.254476589496265e-1 1.422260336332033e-1 1.422260271166027e-1
          4.202025123375888e-2 4.202025003843036e-2
          </occupations>
      </ks_energies>
    </band_structure>
    <forces rank="2" dims="3 3" order="F">
      0.000000000000000e0 0.000000000000000e0 0.000000000000000e0
      0.000000000000000e0 0.000000000000000e0 1.636716241288673e-6
      0.000000000000000e0 3.979774577715801e-26 -1.636716241288673e-6
      </forces>
  </output>
  <status>0</status>
  <timing_info>
    <total label="PWSCF">
      <cpu>1.968466000000000e0</cpu>
      <wall>3.965957164764404e0</wall>
    </total>
    <partial label="electrons" calls="8">
      <cpu>1.546619000000000e0</cpu>
      <wall>1.790718317031860e0</wall>
    </partial>
  </timing_info>
  <closed DATE="11 Jun 2026" TIME="21: 2: 0"></closed>
</qes:espresso>
